setup.py
src/subdicts/__init__.py
src/subdicts/utils.py
src/subdicts.egg-info/PKG-INFO
src/subdicts.egg-info/SOURCES.txt
src/subdicts.egg-info/dependency_links.txt
src/subdicts.egg-info/requires.txt
src/subdicts.egg-info/top_level.txt
src/subdicts/tests/__init__.py
src/subdicts/tests/test_subdicts.py