Metadata-Version: 1.1
Name: subdicts
Version: 1.0.3
Summary: A small python utility which parses nested-keys in dictionaries into sub-dictionaries.
Home-page: https://github.com/arnellebalane/subdicts
Author: Arnelle Balane
Author-email: arnellebalane@gmail.com
License: MIT
Platform: UNKNOWN
Classifier: Development Status :: 3 - Alpha
Classifier: Intended Audience :: Developers
Classifier: License :: OSI Approved :: MIT License
Classifier: Operating System :: OS Independent
Classifier: Programming Language :: Python
Classifier: Programming Language :: Python :: 2.7
